arbutus.py
arbutus-0.0.4.dist-info/METADATA
arbutus-0.0.4.dist-info/WHEEL
arbutus-0.0.4.dist-info/licenses/LICENSE
arbutus-0.0.4.dist-info/RECORD
