Metadata-Version: 2.1
Name: arbutus
Version: 0.0.4
Summary: Simplification of CLI construction in Python based on argparse: just add branches and arguments. CLI construction from yaml file also available.
Project-URL: Homepage, https://github.com/aubravo/arbutus
Project-URL: Bug Tracker, https://github.com/aubravo/arbutus/issues
Author-email: Alvaro Bravo <alvaroubravo@gmail.com>
License-File: LICENSE
Classifier: License :: OSI Approved :: MIT License
Classifier: Operating System :: OS Independent
Classifier: Programming Language :: Python :: 3
Requires-Python: >=3.8
